demo-toronto/tasks/__init__.py
demo-toronto/tasks/task_ask_food_type.py
demo-toronto/tasks/task_ask_location.py
demo-toronto/tasks/task_ask_purpose.py
demo-toronto/tasks/task_critiquing.py
demo-toronto/tasks/task_greeting.py
demo-toronto/tasks/task_recommend.py
neureca/__init__.py
neureca/cmd.py
neureca/dialogue_manager/__init__.py
neureca/dialogue_manager/manager.py
neureca/dialogue_manager/stage.py
neureca/dialogue_manager/task.py
neureca/dialogue_manager/text.py
neureca/dialogue_manager/user_belief.py
neureca/explainer/__init__.py
neureca/explainer/explainer.py
neureca/explainer/utils/__init__.py
neureca/explainer/utils/parse_attribute.py
neureca/interface/__init__.py
neureca/interface/neureca.py
neureca/interface/static/css/bootstrap.css
neureca/interface/static/css/bootstrap.css.map
neureca/interface/static/css/bootstrap.min.css
neureca/interface/static/css/bootstrap.min.css.map
neureca/interface/static/css/main.css
neureca/interface/static/js/bootstrap.js
neureca/interface/static/js/bootstrap.js.map
neureca/interface/static/js/bootstrap.min.js
neureca/interface/static/js/bootstrap.min.js.map
neureca/interface/static/js/jquery.js
neureca/interface/static/js/main.js
neureca/interface/templates/index.html
neureca/nlu/__init__.py
neureca/nlu/nlu.py
neureca/nlu/trainer.py
neureca/nlu/data/__init__.py
neureca/nlu/data/attribute.py
neureca/nlu/data/base_nlu_data.py
neureca/nlu/data/intent.py
neureca/nlu/data/utils.py
neureca/nlu/featurizers/__init__.py
neureca/nlu/featurizers/base_featurizer.py
neureca/nlu/featurizers/bert.py
neureca/nlu/lit_wrappers/__init__.py
neureca/nlu/lit_wrappers/classifier.py
neureca/nlu/lit_wrappers/crf_recognizer.py
neureca/recommender/__init__.py
neureca/recommender/recommender.py
neureca/recommender/trainer.py
neureca/recommender/data/__init__.py
neureca/recommender/data/user_based.py
neureca/recommender/data/utils.py
neureca/recommender/lit_wrappers/__init__.py
neureca/recommender/lit_wrappers/explicit_rating_wrapper.py
neureca-0.0.1.dist-info/LICENSE
neureca-0.0.1.dist-info/METADATA
neureca-0.0.1.dist-info/WHEEL
neureca-0.0.1.dist-info/entry_points.txt
neureca-0.0.1.dist-info/top_level.txt
neureca-0.0.1.dist-info/RECORD
